windwardrestapi-23.0.0.3.data/purelib/windwardrestapi/__init__.py
windwardrestapi-23.0.0.3.data/purelib/windwardrestapi/Api/ApiException.py
windwardrestapi-23.0.0.3.data/purelib/windwardrestapi/Api/WindwardClient.py
windwardrestapi-23.0.0.3.data/purelib/windwardrestapi/Api/__init__.py
windwardrestapi-23.0.0.3.data/purelib/windwardrestapi/Model/DataSet.py
windwardrestapi-23.0.0.3.data/purelib/windwardrestapi/Model/DataSetProfile.py
windwardrestapi-23.0.0.3.data/purelib/windwardrestapi/Model/DataSourceProfile.py
windwardrestapi-23.0.0.3.data/purelib/windwardrestapi/Model/Datasource.py
windwardrestapi-23.0.0.3.data/purelib/windwardrestapi/Model/Document.py
windwardrestapi-23.0.0.3.data/purelib/windwardrestapi/Model/DocumentMeta.py
windwardrestapi-23.0.0.3.data/purelib/windwardrestapi/Model/Entry.py
windwardrestapi-23.0.0.3.data/purelib/windwardrestapi/Model/ImportMetrics.py
windwardrestapi-23.0.0.3.data/purelib/windwardrestapi/Model/Issue.py
windwardrestapi-23.0.0.3.data/purelib/windwardrestapi/Model/JsonDataSource.py
windwardrestapi-23.0.0.3.data/purelib/windwardrestapi/Model/JsonXpathDataSource.py
windwardrestapi-23.0.0.3.data/purelib/windwardrestapi/Model/Metrics.py
windwardrestapi-23.0.0.3.data/purelib/windwardrestapi/Model/ODataDataSource.py
windwardrestapi-23.0.0.3.data/purelib/windwardrestapi/Model/Parameter.py
windwardrestapi-23.0.0.3.data/purelib/windwardrestapi/Model/ParameterValue.py
windwardrestapi-23.0.0.3.data/purelib/windwardrestapi/Model/Property.py
windwardrestapi-23.0.0.3.data/purelib/windwardrestapi/Model/SalesforceDataSource.py
windwardrestapi-23.0.0.3.data/purelib/windwardrestapi/Model/SalesforceOAuthDataSource.py
windwardrestapi-23.0.0.3.data/purelib/windwardrestapi/Model/ServiceError.py
windwardrestapi-23.0.0.3.data/purelib/windwardrestapi/Model/SqlDataSource.py
windwardrestapi-23.0.0.3.data/purelib/windwardrestapi/Model/TagTree.py
windwardrestapi-23.0.0.3.data/purelib/windwardrestapi/Model/Template.py
windwardrestapi-23.0.0.3.dist-info/METADATA
windwardrestapi-23.0.0.3.dist-info/WHEEL
windwardrestapi-23.0.0.3.dist-info/top_level.txt
windwardrestapi-23.0.0.3.dist-info/RECORD
