Metadata-Version: 2.1
Name: windwardrestapi
Version: 23.0.0.3
Summary: Python client for the Windward RESTful Engine
Home-page: http://www.windward.net/products/restful/
Author: Windward Studios
Author-email: support@windward.net
License: UNKNOWN
Platform: UNKNOWN
Requires-Dist: requests
Requires-Dist: six
